mot/__init__.py
mot/__version__.py
mot/configuration.py
mot/mcmc_diagnostics.py
mot/random.py
mot/stats.py
mot/cl_routines/__init__.py
mot/cl_routines/numerical_differentiation.py
mot/data/opencl/bracket_spf.cl
mot/data/opencl/complex.h
mot/data/opencl/euclidian_norm.cl
mot/data/opencl/lmmin.cl
mot/data/opencl/nmsimplex_spf.cl
mot/data/opencl/powell.cl
mot/data/opencl/subplex.cl
mot/data/opencl/cerf/im_w_of_x.cl
mot/data/opencl/random123/array.h
mot/data/opencl/random123/openclfeatures.h
mot/data/opencl/random123/philox.h
mot/data/opencl/random123/rand123.h
mot/data/opencl/random123/threefry.h
mot/lib/__init__.py
mot/lib/cl_environments.py
mot/lib/cl_function.py
mot/lib/cl_processors.py
mot/lib/kernel_data.py
mot/lib/load_balancers.py
mot/lib/utils.py
mot/library_functions/__init__.py
mot/library_functions/base.py
mot/library_functions/eispack.py
mot/library_functions/error_functions.py
mot/library_functions/lanczos.py
mot/library_functions/legendre_polynomial.py
mot/library_functions/optimize.py
mot/library_functions/polynomials.py
mot/library_functions/special_functions.py
mot/library_functions/unity.py
mot/library_functions/continuous_distributions/__init__.py
mot/library_functions/continuous_distributions/gamma.py
mot/library_functions/continuous_distributions/invgamma.py
mot/library_functions/continuous_distributions/normal.py
mot/optimize/__init__.py
mot/optimize/base.py
mot/sample/__init__.py
mot/sample/amwg.py
mot/sample/base.py
mot/sample/mwg.py
mot/sample/scam.py
mot/sample/t_walk.py
tests/__init__.py
tests/test_cl_routines.py
tests/utils.py
tests/library_functions/__init__.py
tests/library_functions/error_functions.py
tests/library_functions/gamma.py
tests/library_functions/invgamma.py
tests/library_functions/normal.py
mot-0.11.4.dist-info/LICENSE
mot-0.11.4.dist-info/METADATA
mot-0.11.4.dist-info/WHEEL
mot-0.11.4.dist-info/top_level.txt
mot-0.11.4.dist-info/RECORD
